re6st/__init__.py
re6st/cache.py
re6st/ctl.py
re6st/debug.py
re6st/multicast.py
re6st/ovpn-client
re6st/ovpn-server
re6st/plib.py
re6st/registry.py
re6st/tunnel.py
re6st/upnpigd.py
re6st/utils.py
re6st/x509.py
re6st/cli/__init__.py
re6st/cli/conf.py
re6st/cli/node.py
re6st/cli/registry.py
re6st/version.py
re6stnet-0.642.dist-info/METADATA
re6stnet-0.642.dist-info/WHEEL
re6stnet-0.642.dist-info/entry_points.txt
re6stnet-0.642.dist-info/licenses/COPYING
re6stnet-0.642.dist-info/RECORD
