Metadata-Version: 2.3
Name: re6stnet
Version: 0.642
Summary: Resilient, Scalable, IPv6 Network
Project-URL: Homepage, http://re6st.net
Author-email: Nexedi <re6stnet@erp5.org>
License: GPL-2.0-or-later
Classifier: Environment :: Console
Classifier: Operating System :: POSIX :: Linux
Classifier: Topic :: Internet
Classifier: Topic :: System :: Networking
Requires-Python: >=3.11
Requires-Dist: miniupnpc
Requires-Dist: pyopenssl>=0.13
Provides-Extra: geoip
Requires-Dist: geoip2; extra == 'geoip'
Provides-Extra: multicast
Requires-Dist: pyyaml; extra == 'multicast'
Provides-Extra: test
Requires-Dist: mock; extra == 'test'
Requires-Dist: multiping; extra == 'test'
Requires-Dist: nemu3; extra == 'test'
Requires-Dist: psutil; extra == 'test'
Requires-Dist: unshare; extra == 'test'
